README.rst
setup.py
django_template_goodies.egg-info/PKG-INFO
django_template_goodies.egg-info/SOURCES.txt
django_template_goodies.egg-info/dependency_links.txt
django_template_goodies.egg-info/not-zip-safe
django_template_goodies.egg-info/requires.txt
django_template_goodies.egg-info/top_level.txt
template_goodies/__init__.py
template_goodies/templatetags/__init__.py
template_goodies/templatetags/goodies.py