Metadata-Version: 1.1
Name: django-template-goodies
Version: 0.1.5
Summary: A set of django template tools.
Home-page: https://github.com/jqb/django-template-goodies/
Author: Jakub Janoszek
Author-email: kuba.janoszek@gmail.com
License: UNKNOWN
Platform: UNKNOWN
Classifier: Development Status :: 4 - Beta
Classifier: Framework :: Django
Classifier: Environment :: Web Environment
Classifier: Intended Audience :: Developers
Classifier: License :: OSI Approved :: BSD License
Classifier: Operating System :: OS Independent
Classifier: Programming Language :: Python
